0xnetx_logx-0.0.2.dist-info/licenses/LICENSE
logx/__init__.py
logx/constant.py
logx/example.py
logx/loggerz.py
logx/logx.py
logx/opt.py
logx/setup.py
0xnetx_logx-0.0.2.dist-info/METADATA
0xnetx_logx-0.0.2.dist-info/WHEEL
0xnetx_logx-0.0.2.dist-info/top_level.txt
0xnetx_logx-0.0.2.dist-info/RECORD
