Metadata-Version: 2.4
Name: 0xnetx-logx
Version: 0.0.2
Summary: A Python logging library compatible with NETSTARS log specification v1.3
Home-page: https://github.com/0xNetx/logx
Author: 0xNetx
Author-email: 
License: MIT
Project-URL: Homepage, https://github.com/0xNetx/logx
Project-URL: Repository, https://github.com/0xNetx/logx
Project-URL: Issues, https://github.com/0xNetx/logx/issues
Keywords: logging,structured-logging,netstars,log-specification
Classifier: Development Status :: 3 - Alpha
Classifier: Intended Audience :: Developers
Classifier: Topic :: Software Development :: Libraries :: Python Modules
Classifier: Programming Language :: Python :: 3
Classifier: Programming Language :: Python :: 3.8
Classifier: Programming Language :: Python :: 3.9
Classifier: Programming Language :: Python :: 3.10
Classifier: Programming Language :: Python :: 3.11
Classifier: License :: OSI Approved :: MIT License
Classifier: Operating System :: OS Independent
Requires-Python: >=3.8
License-File: LICENSE
Dynamic: home-page
Dynamic: license-file
Dynamic: requires-python
